CHANGELOG.txt
LICENSE.txt
MANIFEST.in
README.txt
__init__.py
setup.py
Genetic_Algorithm_VEDA.egg-info/PKG-INFO
Genetic_Algorithm_VEDA.egg-info/SOURCES.txt
Genetic_Algorithm_VEDA.egg-info/dependency_links.txt
Genetic_Algorithm_VEDA.egg-info/top_level.txt
dist/Genetic_Algorithm_VEDA-0.0.2/CHANGELOG.txt
dist/Genetic_Algorithm_VEDA-0.0.2/LICENSE.txt
dist/Genetic_Algorithm_VEDA-0.0.2/README.txt
dist/Genetic_Algorithm_VEDA-0.0.2/__init__.py
dist/Genetic_Algorithm_VEDA-0.0.2/setup.py
dist/Genetic_Algorithm_VEDA-0.0.2/Genetic_Algorithm_VEDA.egg-info/SOURCES.txt
dist/Genetic_Algorithm_VEDA-0.0.2/Genetic_Algorithm_VEDA.egg-info/dependency_links.txt
dist/Genetic_Algorithm_VEDA-0.0.2/Genetic_Algorithm_VEDA.egg-info/top_level.txt